[
  { "word": "bateau", "synonyms": [ { "word": "navire", "score": 3 }, { "word": "embarcation", "score": 2 } ] },
  { "word": "fauteuil", "synonyms": [ { "word": "chaise confortable", "score": 3 }, { "word": "siège", "score": 2 } ] },
  { "word": "bol", "synonyms": [ { "word": "récipient", "score": 3 }, { "word": "tasse", "score": 2 } ] },
  { "word": "instruire", "synonyms": [ { "word": "enseigner", "score": 3 }, { "word": "former", "score": 2 } ] },
  { "word": "hier", "synonyms": [ { "word": "la veille", "score": 3 }, { "word": "le jour passé", "score": 2 } ] },
  { "word": "arracher", "synonyms": [ { "word": "retirer", "score": 3 }, { "word": "extraire", "score": 2 } ] },
  { "word": "sanction", "synonyms": [ { "word": "punition", "score": 3 }, { "word": "mesure disciplinaire", "score": 2 } ] },
  { "word": "refuge", "synonyms": [ { "word": "abri", "score": 3 }, { "word": "asile", "score": 2 } ] },
  { "word": "calendrier", "synonyms": [ { "word": "agenda", "score": 3 }, { "word": "planning", "score": 2 } ] },
  { "word": "baleine", "synonyms": [ { "word": "cétacé", "score": 3 }, { "word": "mammifère marin", "score": 2 } ] },
  { "word": "mime", "synonyms": [ { "word": "pantomime", "score": 3 }, { "word": "acteur silencieux", "score": 2 } ] },
  { "word": "persévérer", "synonyms": [ { "word": "tenir bon", "score": 3 }, { "word": "continuer", "score": 2 } ] },
  { "word": "sauvage", "synonyms": [ { "word": "feroce", "score": 3 }, { "word": "indompté", "score": 2 } ] },
  { "word": "héréditaire", "synonyms": [ { "word": "génétique", "score": 3 }, { "word": "transmis", "score": 2 } ] },
  { "word": "connivence", "synonyms": [ { "word": "complicité", "score": 3 }, { "word": "accord secret", "score": 2 } ] },
  { "word": "grandiose", "synonyms": [ { "word": "magnifique", "score": 3 }, { "word": "imposant", "score": 2 } ] },
  { "word": "confier", "synonyms": [ { "word": "remettre", "score": 3 }, { "word": "dévoiler", "score": 2 } ] },
  { "word": "vigoureux", "synonyms": [ { "word": "énergique", "score": 3 }, { "word": "fort", "score": 2 } ] },
  { "word": "contracter", "synonyms": [ { "word": "acquérir", "score": 3 }, { "word": "réduire", "score": 2 } ] },
  { "word": "initiative", "synonyms": [ { "word": "proposition", "score": 3 }, { "word": "démarche", "score": 2 } ] },
  { "word": "esquisse", "synonyms": [ { "word": "croquis", "score": 3 }, { "word": "ébauche", "score": 2 } ] },
  { "word": "irritable", "synonyms": [ { "word": "nerveux", "score": 3 }, { "word": "susceptible", "score": 2 } ] },
  { "word": "invectiver", "synonyms": [ { "word": "insulter", "score": 3 }, { "word": "réprimander", "score": 2 } ] },
  { "word": "hétérogène", "synonyms": [ { "word": "varié", "score": 3 }, { "word": "composite", "score": 2 } ] },
  { "word": "assimiler", "synonyms": [ { "word": "comprendre", "score": 3 }, { "word": "intégrer", "score": 2 } ] },
  { "word": "concertation", "synonyms": [ { "word": "discussion", "score": 3 }, { "word": "consultation", "score": 2 } ] },
  { "word": "émulation", "synonyms": [ { "word": "rivalité", "score": 3 }, { "word": "motivation", "score": 2 } ] },
  { "word": "pittoresque", "synonyms": [ { "word": "charmant", "score": 3 }, { "word": "coloré", "score": 2 } ] },
  { "word": "évasif", "synonyms": [ { "word": "vague", "score": 3 }, { "word": "indéfini", "score": 2 } ] },
  { "word": "élaborer", "synonyms": [ { "word": "développer", "score": 3 }, { "word": "préparer", "score": 2 } ] },
  { "word": "prosaïque", "synonyms": [ { "word": "banal", "score": 3 }, { "word": "ordinaire", "score": 2 } ] },
  { "word": "apologie", "synonyms": [ { "word": "défense", "score": 3 }, { "word": "justification", "score": 2 } ] },
  { "word": "conjecture", "synonyms": [ { "word": "supposition", "score": 3 }, { "word": "hypothèse", "score": 2 } ] }
]
